scrapy_smawe/__init__.py
scrapy_smawe/downloader_middleware.py
scrapy_samwe-0.1.dist-info/METADATA
scrapy_samwe-0.1.dist-info/WHEEL
scrapy_samwe-0.1.dist-info/top_level.txt
scrapy_samwe-0.1.dist-info/RECORD
